seamless_3dep/__init__.py
seamless_3dep/_vrt_pools.py
seamless_3dep/seamless_3dep.py
seamless_3dep-0.3.1.dist-info/METADATA
seamless_3dep-0.3.1.dist-info/WHEEL
seamless_3dep-0.3.1.dist-info/licenses/AUTHORS.md
seamless_3dep-0.3.1.dist-info/licenses/LICENSE
seamless_3dep-0.3.1.dist-info/RECORD
